text2output.py
text2output-1.1.0.dist-info/LICENSE.txt
text2output-1.1.0.dist-info/METADATA
text2output-1.1.0.dist-info/WHEEL
text2output-1.1.0.dist-info/top_level.txt
text2output-1.1.0.dist-info/RECORD
