Metadata-Version: 2.1
Name: text2output
Version: 1.1.0
Summary: Convert your text to print function in any language
Home-page: https://github.com/orishamir/
Author: Ori Shamir
License: UNKNOWN
Platform: UNKNOWN
Classifier: Programming Language :: Python :: 3.7
Classifier: Development Status :: 4 - Beta
Classifier: License :: OSI Approved :: MIT License
Classifier: Natural Language :: English
Classifier: Topic :: Artistic Software
Classifier: Operating System :: OS Independent
